cmc_unofficial_wyt/__init__.py
cmc_unofficial_wyt/core.py
cmc_unofficial_wyt/utils.py
cmc_unofficial_wyt-1.0.dist-info/LICENCE.txt
cmc_unofficial_wyt-1.0.dist-info/METADATA
cmc_unofficial_wyt-1.0.dist-info/WHEEL
cmc_unofficial_wyt-1.0.dist-info/top_level.txt
cmc_unofficial_wyt-1.0.dist-info/RECORD
