Metadata-Version: 2.1
Name: cmc-unofficial-wyt
Version: 1.0
Summary: cmc wrapper
Home-page: https://github.com/wytxty/cmc_unofficial_wyt
Author: wytxty
Author-email: yvettewkkaa@gmail.com
License: MIT
License-File: LICENCE.txt
